LICENSE
MANIFEST.in
README.md
README.txt
requirements_as_lib.txt
setup.py
src/dev_cli/__init__.py
src/dev_cli/__main__.py
src/dev_cli/api.py
src/dev_cli/constants.py
src/dev_cli/errors.py
src/dev_cli/models.py
src/dev_cli/parser.py
src/dev_cli/utils.py
src/dev_cli.egg-info/PKG-INFO
src/dev_cli.egg-info/SOURCES.txt
src/dev_cli.egg-info/dependency_links.txt
src/dev_cli.egg-info/requires.txt
src/dev_cli.egg-info/top_level.txt