Metadata-Version: 1.1
Name: dev-cli
Version: 0.2.0
Summary: A CLI interface for dev.to
Home-page: https://github.com/Xowap/DEV-CLI
Author: Rémy Sanchez
Author-email: remy.sanchez@hyperthese.net
License: WTFPL
Platform: UNKNOWN
Classifier: Development Status :: 3 - Alpha
Classifier: Programming Language :: Python :: 3.6
Classifier: Programming Language :: Python :: 3.7
Classifier: Programming Language :: Python :: 3.8
Classifier: Programming Language :: Python :: 3 :: Only
